[
  {
    "id": "rsa-can",
    "status": "finished",
    "scoreA": "0",
    "scoreB": "1",
    "winnerId": "can",
    "minute": null
  },
  {
    "id": "ned-mar",
    "status": "finished",
    "scoreA": "1 (2)",
    "scoreB": "1 (3)",
    "winnerId": "mar",
    "minute": null
  },
  {
    "id": "ger-par",
    "status": "finished",
    "scoreA": "1 (3)",
    "scoreB": "1 (4)",
    "winnerId": "par",
    "minute": null
  },
  {
    "id": "fra-swe",
    "status": "finished",
    "scoreA": "3",
    "scoreB": "0",
    "winnerId": "fra",
    "minute": null
  },
  {
    "id": "bel-sen",
    "status": "finished",
    "scoreA": "3",
    "scoreB": "2",
    "winnerId": "bel",
    "minute": null
  },
  {
    "id": "usa-bih",
    "status": "finished",
    "scoreA": "2",
    "scoreB": "0",
    "winnerId": "usa",
    "minute": null
  },
  {
    "id": "esp-aut",
    "status": "finished",
    "scoreA": "3",
    "scoreB": "0",
    "winnerId": "esp",
    "minute": null
  },
  {
    "id": "por-cro",
    "status": "finished",
    "scoreA": "2",
    "scoreB": "1",
    "winnerId": "por",
    "minute": null
  },
  {
    "id": "bra-jpn",
    "status": "finished",
    "scoreA": "2",
    "scoreB": "1",
    "winnerId": "bra",
    "minute": null
  },
  {
    "id": "civ-nor",
    "status": "finished",
    "scoreA": "1",
    "scoreB": "2",
    "winnerId": "nor",
    "minute": null
  },
  {
    "id": "mex-ecu",
    "status": "finished",
    "scoreA": "2",
    "scoreB": "0",
    "winnerId": "mex",
    "minute": null
  },
  {
    "id": "eng-cod",
    "status": "finished",
    "scoreA": "2",
    "scoreB": "1",
    "winnerId": "eng",
    "minute": null
  },
  {
    "id": "sui-alg",
    "status": "finished",
    "scoreA": "2",
    "scoreB": "0",
    "winnerId": "sui",
    "minute": null
  },
  {
    "id": "aus-egy",
    "status": "finished",
    "scoreA": "1 (2)",
    "scoreB": "1 (4)",
    "winnerId": "egy",
    "minute": null
  }
]